docker_charon/__init__.py
docker_charon/__main__.py
docker_charon/common.py
docker_charon/decoder.py
docker_charon/encoder.py
docker_charon/test_utils.py
docker_charon-0.4.3.dist-info/LICENSE
docker_charon-0.4.3.dist-info/METADATA
docker_charon-0.4.3.dist-info/WHEEL
docker_charon-0.4.3.dist-info/entry_points.txt
docker_charon-0.4.3.dist-info/top_level.txt
docker_charon-0.4.3.dist-info/RECORD
