Metadata-Version: 2.1
Name: docker-charon
Version: 0.4.3
Summary: A tool to move your Docker images to an air-gapped registry.
License: MIT
Requires-Python: >=3.8, <4
License-File: LICENSE
Requires-Dist: python-dxf ==7.8.0
Requires-Dist: tqdm
Requires-Dist: typer
Requires-Dist: pydantic <3,>=1.5
